[
  {
    "ContainingType": "ComputadorController",
    "Method": "CrearEscritorio",
    "RelativePath": "api/Computador/escritorio/{marca}",
    "HttpMethod": "GET",
    "IsController": true,
    "Order": 0,
    "Parameters": [
      {
        "Name": "marca",
        "Type": "System.String",
        "IsRequired": true
      }
    ],
    "ReturnTypes": []
  },
  {
    "ContainingType": "ComputadorController",
    "Method": "ObtenerEscritorios",
    "RelativePath": "api/Computador/escritorios",
    "HttpMethod": "GET",
    "IsController": true,
    "Order": 0,
    "Parameters": [],
    "ReturnTypes": []
  },
  {
    "ContainingType": "ComputadorController",
    "Method": "PersonalizarEscritorio",
    "RelativePath": "api/Computador/personalizar/escritorio",
    "HttpMethod": "POST",
    "IsController": true,
    "Order": 0,
    "Parameters": [
      {
        "Name": "personalizacion",
        "Type": "PersonalizacionComputadorDto",
        "IsRequired": true
      }
    ],
    "ReturnTypes": []
  },
  {
    "ContainingType": "ComputadorController",
    "Method": "PersonalizarPortatil",
    "RelativePath": "api/Computador/personalizar/portatil",
    "HttpMethod": "POST",
    "IsController": true,
    "Order": 0,
    "Parameters": [
      {
        "Name": "personalizacion",
        "Type": "PersonalizacionComputadorDto",
        "IsRequired": true
      }
    ],
    "ReturnTypes": []
  },
  {
    "ContainingType": "ComputadorController",
    "Method": "CrearPortatil",
    "RelativePath": "api/Computador/portatil/{marca}",
    "HttpMethod": "GET",
    "IsController": true,
    "Order": 0,
    "Parameters": [
      {
        "Name": "marca",
        "Type": "System.String",
        "IsRequired": true
      }
    ],
    "ReturnTypes": []
  },
  {
    "ContainingType": "ComputadorController",
    "Method": "ObtenerPortatiles",
    "RelativePath": "api/Computador/portatiles",
    "HttpMethod": "GET",
    "IsController": true,
    "Order": 0,
    "Parameters": [],
    "ReturnTypes": []
  },
  {
    "ContainingType": "TiendaGamer.Controllers.WeatherForecastController",
    "Method": "Get",
    "RelativePath": "WeatherForecast",
    "HttpMethod": "GET",
    "IsController": true,
    "Order": 0,
    "Parameters": [],
    "ReturnTypes": [
      {
        "Type": "System.Collections.Generic.IEnumerable\u00601[[TiendaGamer.WeatherForecast, TiendaGamer, Version=1.0.0.0, Culture=neutral, PublicKeyToken=null]]",
        "MediaTypes": [
          "text/plain",
          "application/json",
          "text/json"
        ],
        "StatusCode": 200
      }
    ],
    "EndpointName": "GetWeatherForecast"
  }
]